pysugarcrm/pysugarcrm.py
pysugarcrm/__init__.py
pysugarcrm-1.0.3.dist-info/DESCRIPTION.rst
pysugarcrm-1.0.3.dist-info/top_level.txt
pysugarcrm-1.0.3.dist-info/METADATA
pysugarcrm-1.0.3.dist-info/metadata.json
pysugarcrm-1.0.3.dist-info/WHEEL
pysugarcrm-1.0.3.dist-info/RECORD
