Metadata-Version: 2.0
Name: pysugarcrm
Version: 1.0.3
Summary: API Wrapper for SugarCRM v10
Home-page: https://github.com/Feverup/pysugarcrm
Author: Diego Navarro
Author-email: diego@feverup.com
License: BSD
Keywords: pysugarcrm
Platform: UNKNOWN
Classifier: Development Status :: 5 - Production/Stable
Classifier: Intended Audience :: Developers
Classifier: License :: OSI Approved :: BSD License
Classifier: Natural Language :: English
Classifier: Programming Language :: Python :: 2
Classifier: Programming Language :: Python :: 2.6
Classifier: Programming Language :: Python :: 2.7
Classifier: Programming Language :: Python :: 3
Classifier: Programming Language :: Python :: 3.5
Classifier: Programming Language :: Python :: 3.6
Requires-Dist: requests (>=2.7.0)
